jupyter_multiselection/__init__.py
jupyter_multiselection/static/multiselection/README.md
jupyter_multiselection/static/multiselection/icon.png
jupyter_multiselection/static/multiselection/multiselection.css
jupyter_multiselection/static/multiselection/multiselection.js
jupyter_multiselection/static/multiselection/multiselection.yml
jupyter_multiselection/static/multiselection/multiselection1.gif
jupyter_multiselection/static/multiselection/multiselection2.gif
jupyter_multiselection-0.1.1.dist-info/LICENSE
jupyter_multiselection-0.1.1.dist-info/METADATA
jupyter_multiselection-0.1.1.dist-info/WHEEL
jupyter_multiselection-0.1.1.dist-info/top_level.txt
jupyter_multiselection-0.1.1.dist-info/RECORD
