Metadata-Version: 2.1
Name: jupyter-multiselection
Version: 0.1.1
Summary: A nbextension to select occurences of the currently selected text
Home-page: https://gitlab.com/chdudek/jupyter_multiselection
Author: Christian-Alexander Dudek
Author-email: christian@dudek.me
License: UNKNOWN
Platform: UNKNOWN
Classifier: Programming Language :: Python :: 3
Classifier: Development Status :: 4 - Beta
Classifier: Framework :: IPython
Classifier: Framework :: Jupyter
Classifier: Intended Audience :: Developers
Classifier: Intended Audience :: Science/Research
Classifier: License :: OSI Approved :: GNU General Public License v3 (GPLv3)
Classifier: Operating System :: OS Independent
Classifier: Programming Language :: JavaScript
Classifier: Topic :: Scientific/Engineering :: Information Analysis
Classifier: Topic :: Scientific/Engineering :: Bio-Informatics
Classifier: Topic :: Utilities
Requires-Python: >=3.6
